LICENSE
README.md
setup.cfg
setup.py
cli_yams.egg-info/PKG-INFO
cli_yams.egg-info/SOURCES.txt
cli_yams.egg-info/dependency_links.txt
cli_yams.egg-info/entry_points.txt
cli_yams.egg-info/requires.txt
cli_yams.egg-info/top_level.txt
yams/__init__.py
yams/info.py
yams/pipelines.py
yams/settings.py
yams/utils.py
yams/commands/__init__.py
yams/commands/__main__.py
yams/commands/info.py
yams/commands/start/__init__.py
yams/commands/start/newspaper.py
yams/spiders/__init__.py
yams/spiders/grupocomercio.py